exhibition/__init__.py
exhibition/_version.py
exhibition/command.py
exhibition/config.py
exhibition/node.py
exhibition/utils.py
exhibition/data/starter/README.md
exhibition/data/starter/site.yaml
exhibition/data/starter/content/index.html
exhibition/data/starter/templates/page.j2
exhibition/filters/__init__.py
exhibition/filters/base.py
exhibition/filters/external.py
exhibition/filters/jinja2.py
exhibition/filters/markdown.py
exhibition/filters/pandoc.py
exhibition/tests/__init__.py
exhibition/tests/test_command.py
exhibition/tests/test_config.py
exhibition/tests/test_filters.py
exhibition/tests/test_gen.py
exhibition/tests/test_node.py
exhibition/tests/test_serve.py
exhibition-0.2.3.dist-info/LICENSE
exhibition-0.2.3.dist-info/METADATA
exhibition-0.2.3.dist-info/WHEEL
exhibition-0.2.3.dist-info/entry_points.txt
exhibition-0.2.3.dist-info/top_level.txt
exhibition-0.2.3.dist-info/RECORD
