Metadata-Version: 2.1
Name: exhibition
Version: 0.2.3
Summary: A Python static site generator
Home-page: https://github.com/moggers87/exhibition
Author: Matt Molyneaux
Author-email: moggers87+git@moggers87.co.uk
License: GPLv3
Download-URL: https://pypi.org/project/exhibition/
Platform: UNKNOWN
Classifier: Development Status :: 3 - Alpha
Classifier: Intended Audience :: Developers
Classifier: License :: OSI Approved :: GNU General Public License v3 or later (GPLv3+)
Classifier: Programming Language :: Python :: 3
Classifier: Programming Language :: Python :: 3.8
Classifier: Programming Language :: Python :: 3.9
Classifier: Programming Language :: Python :: 3.10
Classifier: Topic :: Internet :: WWW/HTTP :: Site Management
Classifier: Topic :: Internet
Classifier: Topic :: Software Development :: Build Tools
Classifier: Topic :: Software Development :: Code Generators
Classifier: Topic :: Software Development
Requires-Python: >=3.8
License-File: LICENSE
Requires-Dist: click
Requires-Dist: jinja2 (<3.1)
Requires-Dist: markdown
Requires-Dist: ruamel.yaml
Requires-Dist: typogrify
Requires-Dist: pypandoc
Provides-Extra: docs
Requires-Dist: sphinx ; extra == 'docs'
Requires-Dist: sphinx-rtd-theme ; extra == 'docs'
Requires-Dist: sphinx-click ; extra == 'docs'
